{
  "paper_id": "PMC4430214",
  "sections": [
    {
      "id": 0,
      "section": "ABSTRACT",
      "relations": 7,
      "page": 1
    },
    {
      "id": 1,
      "section": "Bead Uptake Assay",
      "relations": 3,
      "page": 3
    },
    {
      "id": 2,
      "section": "Changes in T-cell Surface Molecules upon Stimulation",
      "relations": 11,
      "page": 5
    },
    {
      "id": 3,
      "section": "Cytokine Analysis",
      "relations": 6,
      "page": 4
    },
    {
      "id": 4,
      "section": "Cytokine Production from Stimulated Splenocytes Post-Spaceflight",
      "relations": 17,
      "page": 7
    },
    {
      "id": 5,
      "section": "DISCUSSION",
      "relations": 32,
      "page": 7
    },
    {
      "id": 6,
      "section": "Examination of CD8 expression during stimulation is divided between CD8lo and CD8hi populations.",
      "relations": 3,
      "page": 6
    },
    {
      "id": 7,
      "section": "Flight Information: Subjects and Spaceflight",
      "relations": 6,
      "page": 2
    },
    {
      "id": 8,
      "section": "Flow Cytometry",
      "relations": 3,
      "page": 4
    },
    {
      "id": 9,
      "section": "INTRODUCTION",
      "relations": 44,
      "page": 1
    },
    {
      "id": 10,
      "section": "Mouse Splenocytes Processing",
      "relations": 42,
      "page": 3
    },
    {
      "id": 11,
      "section": "Post-Spaceflight Splenocytes Increased Ability to Uptake Particles",
      "relations": 3,
      "page": 5
    },
    {
      "id": 12,
      "section": "Presentation and Activation Molecule Changes in Splenocytes during TLR Stimulation",
      "relations": 35,
      "page": 6
    },
    {
      "id": 13,
      "section": "Splenocyte Markers Altered Post-Spaceflight",
      "relations": 5,
      "page": 5
    },
    {
      "id": 14,
      "section": "Splenocyte Population Changes between Flight Mice and Ground Controls",
      "relations": 18,
      "page": 4
    },
    {
      "id": 15,
      "section": "Statistics",
      "relations": 0,
      "page": 4
    },
    {
      "id": 16,
      "section": "Stimulation Assays",
      "relations": 36,
      "page": 3
    },
    {
      "id": 17,
      "section": "Synthetic EXPERIMENT",
      "relations": 258,
      "page": null
    },
    {
      "id": 18,
      "section": "Synthetic GENE_PRODUCT",
      "relations": 139,
      "page": null
    },
    {
      "id": 19,
      "section": "Synthetic PHENOTYPE",
      "relations": 24,
      "page": null
    },
    {
      "id": 20,
      "section": "Synthetic CELL_TYPE",
      "relations": 11,
      "page": null
    },
    {
      "id": 21,
      "section": "Synthetic ANATOMICAL_SITE",
      "relations": 3,
      "page": null
    },
    {
      "id": 22,
      "section": "Synthetic PUBLICATION",
      "relations": 0,
      "page": null
    }
  ],
  "edges": [],
  "meta": {
    "total_sections": 17
  }
}