{
  "paper_id": "PMC10503492",
  "section": "DISCUSSION",
  "n_nodes": 15,
  "n_edges": 105,
  "nodes": [
    {
      "id": 448,
      "label": "spatial",
      "type": "GENE_PRODUCT",
      "freq": 1,
      "nav": {
        "section": "DISCUSSION",
        "sentence_id": 95,
        "char_start": 31036,
        "char_end": 31043,
        "anchor": "PMC10503492_31036_31043",
        "page": 16,
        "page_heuristic": true
      }
    },
    {
      "id": 453,
      "label": "glucose",
      "type": "GENE_PRODUCT",
      "freq": 1,
      "nav": {
        "section": "DISCUSSION",
        "sentence_id": 95,
        "char_start": 31218,
        "char_end": 31225,
        "anchor": "PMC10503492_31218_31225",
        "page": 16,
        "page_heuristic": true
      }
    },
    {
      "id": 458,
      "label": "ETC",
      "type": "GENE_PRODUCT",
      "freq": 1,
      "nav": {
        "section": "DISCUSSION",
        "sentence_id": 95,
        "char_start": 31379,
        "char_end": 31382,
        "anchor": "PMC10503492_31379_31382",
        "page": 16,
        "page_heuristic": true
      }
    },
    {
      "id": 460,
      "label": "Study",
      "type": "GENE_PRODUCT",
      "freq": 1,
      "nav": {
        "section": "DISCUSSION",
        "sentence_id": 95,
        "char_start": 31487,
        "char_end": 31492,
        "anchor": "PMC10503492_31487_31492",
        "page": 16,
        "page_heuristic": true
      }
    },
    {
      "id": 461,
      "label": "ETC",
      "type": "GENE_PRODUCT",
      "freq": 1,
      "nav": {
        "section": "DISCUSSION",
        "sentence_id": 95,
        "char_start": 31542,
        "char_end": 31545,
        "anchor": "PMC10503492_31542_31545",
        "page": 16,
        "page_heuristic": true
      }
    },
    {
      "id": 462,
      "label": "abnormal",
      "type": "GENE_PRODUCT",
      "freq": 1,
      "nav": {
        "section": "DISCUSSION",
        "sentence_id": 95,
        "char_start": 31550,
        "char_end": 31558,
        "anchor": "PMC10503492_31550_31558",
        "page": 16,
        "page_heuristic": true
      }
    },
    {
      "id": 474,
      "label": "ROS",
      "type": "GENE_PRODUCT",
      "freq": 1,
      "nav": {
        "section": "DISCUSSION",
        "sentence_id": 95,
        "char_start": 31645,
        "char_end": 31648,
        "anchor": "PMC10503492_31645_31648",
        "page": 16,
        "page_heuristic": true
      }
    },
    {
      "id": 466,
      "label": "ROS",
      "type": "GENE_PRODUCT",
      "freq": 1,
      "nav": {
        "section": "DISCUSSION",
        "sentence_id": 95,
        "char_start": 31645,
        "char_end": 31648,
        "anchor": "PMC10503492_31645_31648",
        "page": 16,
        "page_heuristic": true
      }
    },
    {
      "id": 469,
      "label": "Allaman",
      "type": "GENE_PRODUCT",
      "freq": 1,
      "nav": {
        "section": "DISCUSSION",
        "sentence_id": 95,
        "char_start": 30959,
        "char_end": 30966,
        "anchor": "PMC10503492_30959_30966",
        "page": 16,
        "page_heuristic": true
      }
    },
    {
      "id": 470,
      "label": "Roy",
      "type": "GENE_PRODUCT",
      "freq": 1,
      "nav": {
        "section": "DISCUSSION",
        "sentence_id": 95,
        "char_start": 31099,
        "char_end": 31102,
        "anchor": "PMC10503492_31099_31102",
        "page": 16,
        "page_heuristic": true
      }
    },
    {
      "id": 471,
      "label": "ETC",
      "type": "GENE_PRODUCT",
      "freq": 1,
      "nav": {
        "section": "DISCUSSION",
        "sentence_id": 95,
        "char_start": 31379,
        "char_end": 31382,
        "anchor": "PMC10503492_31379_31382",
        "page": 16,
        "page_heuristic": true
      }
    },
    {
      "id": 473,
      "label": "ETC",
      "type": "GENE_PRODUCT",
      "freq": 1,
      "nav": {
        "section": "DISCUSSION",
        "sentence_id": 95,
        "char_start": 31542,
        "char_end": 31545,
        "anchor": "PMC10503492_31542_31545",
        "page": 16,
        "page_heuristic": true
      }
    },
    {
      "id": 442,
      "label": "dynamic",
      "type": "GENE_PRODUCT",
      "freq": 1,
      "nav": {
        "section": "DISCUSSION",
        "sentence_id": 95,
        "char_start": 30740,
        "char_end": 30747,
        "anchor": "PMC10503492_30740_30747",
        "page": 16,
        "page_heuristic": true
      }
    },
    {
      "id": 475,
      "label": "Bhatti",
      "type": "GENE_PRODUCT",
      "freq": 1,
      "nav": {
        "section": "DISCUSSION",
        "sentence_id": 95,
        "char_start": 31661,
        "char_end": 31667,
        "anchor": "PMC10503492_31661_31667",
        "page": 16,
        "page_heuristic": true
      }
    },
    {
      "id": 444,
      "label": "deriving",
      "type": "GENE_PRODUCT",
      "freq": 1,
      "nav": {
        "section": "DISCUSSION",
        "sentence_id": 95,
        "char_start": 30818,
        "char_end": 30826,
        "anchor": "PMC10503492_30818_30826",
        "page": 16,
        "page_heuristic": true
      }
    }
  ],
  "edges": [
    {
      "id": 557,
      "type": "GENE_PRODUCT_INTERACTS_WITH_GENE_PRODUCT",
      "source": 442,
      "target": 444
    },
    {
      "id": 558,
      "type": "GENE_PRODUCT_INTERACTS_WITH_GENE_PRODUCT",
      "source": 442,
      "target": 448
    },
    {
      "id": 559,
      "type": "GENE_PRODUCT_INTERACTS_WITH_GENE_PRODUCT",
      "source": 442,
      "target": 453
    },
    {
      "id": 560,
      "type": "GENE_PRODUCT_INTERACTS_WITH_GENE_PRODUCT",
      "source": 442,
      "target": 458
    },
    {
      "id": 561,
      "type": "GENE_PRODUCT_INTERACTS_WITH_GENE_PRODUCT",
      "source": 442,
      "target": 460
    },
    {
      "id": 562,
      "type": "GENE_PRODUCT_INTERACTS_WITH_GENE_PRODUCT",
      "source": 442,
      "target": 461
    },
    {
      "id": 563,
      "type": "GENE_PRODUCT_INTERACTS_WITH_GENE_PRODUCT",
      "source": 442,
      "target": 462
    },
    {
      "id": 564,
      "type": "GENE_PRODUCT_INTERACTS_WITH_GENE_PRODUCT",
      "source": 442,
      "target": 466
    },
    {
      "id": 565,
      "type": "GENE_PRODUCT_INTERACTS_WITH_GENE_PRODUCT",
      "source": 442,
      "target": 469
    },
    {
      "id": 566,
      "type": "GENE_PRODUCT_INTERACTS_WITH_GENE_PRODUCT",
      "source": 442,
      "target": 470
    },
    {
      "id": 567,
      "type": "GENE_PRODUCT_INTERACTS_WITH_GENE_PRODUCT",
      "source": 442,
      "target": 471
    },
    {
      "id": 569,
      "type": "GENE_PRODUCT_INTERACTS_WITH_GENE_PRODUCT",
      "source": 442,
      "target": 473
    },
    {
      "id": 570,
      "type": "GENE_PRODUCT_INTERACTS_WITH_GENE_PRODUCT",
      "source": 442,
      "target": 474
    },
    {
      "id": 571,
      "type": "GENE_PRODUCT_INTERACTS_WITH_GENE_PRODUCT",
      "source": 442,
      "target": 475
    },
    {
      "id": 573,
      "type": "GENE_PRODUCT_INTERACTS_WITH_GENE_PRODUCT",
      "source": 444,
      "target": 448
    },
    {
      "id": 574,
      "type": "GENE_PRODUCT_INTERACTS_WITH_GENE_PRODUCT",
      "source": 444,
      "target": 453
    },
    {
      "id": 575,
      "type": "GENE_PRODUCT_INTERACTS_WITH_GENE_PRODUCT",
      "source": 444,
      "target": 458
    },
    {
      "id": 576,
      "type": "GENE_PRODUCT_INTERACTS_WITH_GENE_PRODUCT",
      "source": 444,
      "target": 460
    },
    {
      "id": 577,
      "type": "GENE_PRODUCT_INTERACTS_WITH_GENE_PRODUCT",
      "source": 444,
      "target": 461
    },
    {
      "id": 578,
      "type": "GENE_PRODUCT_INTERACTS_WITH_GENE_PRODUCT",
      "source": 444,
      "target": 462
    },
    {
      "id": 579,
      "type": "GENE_PRODUCT_INTERACTS_WITH_GENE_PRODUCT",
      "source": 444,
      "target": 466
    },
    {
      "id": 580,
      "type": "GENE_PRODUCT_INTERACTS_WITH_GENE_PRODUCT",
      "source": 444,
      "target": 469
    },
    {
      "id": 581,
      "type": "GENE_PRODUCT_INTERACTS_WITH_GENE_PRODUCT",
      "source": 444,
      "target": 470
    },
    {
      "id": 582,
      "type": "GENE_PRODUCT_INTERACTS_WITH_GENE_PRODUCT",
      "source": 444,
      "target": 471
    },
    {
      "id": 584,
      "type": "GENE_PRODUCT_INTERACTS_WITH_GENE_PRODUCT",
      "source": 444,
      "target": 473
    },
    {
      "id": 585,
      "type": "GENE_PRODUCT_INTERACTS_WITH_GENE_PRODUCT",
      "source": 444,
      "target": 474
    },
    {
      "id": 586,
      "type": "GENE_PRODUCT_INTERACTS_WITH_GENE_PRODUCT",
      "source": 444,
      "target": 475
    },
    {
      "id": 588,
      "type": "GENE_PRODUCT_INTERACTS_WITH_GENE_PRODUCT",
      "source": 448,
      "target": 453
    },
    {
      "id": 589,
      "type": "GENE_PRODUCT_INTERACTS_WITH_GENE_PRODUCT",
      "source": 448,
      "target": 458
    },
    {
      "id": 590,
      "type": "GENE_PRODUCT_INTERACTS_WITH_GENE_PRODUCT",
      "source": 448,
      "target": 460
    },
    {
      "id": 591,
      "type": "GENE_PRODUCT_INTERACTS_WITH_GENE_PRODUCT",
      "source": 448,
      "target": 461
    },
    {
      "id": 592,
      "type": "GENE_PRODUCT_INTERACTS_WITH_GENE_PRODUCT",
      "source": 448,
      "target": 462
    },
    {
      "id": 593,
      "type": "GENE_PRODUCT_INTERACTS_WITH_GENE_PRODUCT",
      "source": 448,
      "target": 466
    },
    {
      "id": 594,
      "type": "GENE_PRODUCT_INTERACTS_WITH_GENE_PRODUCT",
      "source": 448,
      "target": 469
    },
    {
      "id": 595,
      "type": "GENE_PRODUCT_INTERACTS_WITH_GENE_PRODUCT",
      "source": 448,
      "target": 470
    },
    {
      "id": 596,
      "type": "GENE_PRODUCT_INTERACTS_WITH_GENE_PRODUCT",
      "source": 448,
      "target": 471
    },
    {
      "id": 598,
      "type": "GENE_PRODUCT_INTERACTS_WITH_GENE_PRODUCT",
      "source": 448,
      "target": 473
    },
    {
      "id": 599,
      "type": "GENE_PRODUCT_INTERACTS_WITH_GENE_PRODUCT",
      "source": 448,
      "target": 474
    },
    {
      "id": 600,
      "type": "GENE_PRODUCT_INTERACTS_WITH_GENE_PRODUCT",
      "source": 448,
      "target": 475
    },
    {
      "id": 602,
      "type": "GENE_PRODUCT_INTERACTS_WITH_GENE_PRODUCT",
      "source": 453,
      "target": 458
    },
    {
      "id": 603,
      "type": "GENE_PRODUCT_INTERACTS_WITH_GENE_PRODUCT",
      "source": 453,
      "target": 460
    },
    {
      "id": 604,
      "type": "GENE_PRODUCT_INTERACTS_WITH_GENE_PRODUCT",
      "source": 453,
      "target": 461
    },
    {
      "id": 605,
      "type": "GENE_PRODUCT_INTERACTS_WITH_GENE_PRODUCT",
      "source": 453,
      "target": 462
    },
    {
      "id": 606,
      "type": "GENE_PRODUCT_INTERACTS_WITH_GENE_PRODUCT",
      "source": 453,
      "target": 466
    },
    {
      "id": 607,
      "type": "GENE_PRODUCT_INTERACTS_WITH_GENE_PRODUCT",
      "source": 453,
      "target": 469
    },
    {
      "id": 608,
      "type": "GENE_PRODUCT_INTERACTS_WITH_GENE_PRODUCT",
      "source": 453,
      "target": 470
    },
    {
      "id": 609,
      "type": "GENE_PRODUCT_INTERACTS_WITH_GENE_PRODUCT",
      "source": 453,
      "target": 471
    },
    {
      "id": 611,
      "type": "GENE_PRODUCT_INTERACTS_WITH_GENE_PRODUCT",
      "source": 453,
      "target": 473
    },
    {
      "id": 612,
      "type": "GENE_PRODUCT_INTERACTS_WITH_GENE_PRODUCT",
      "source": 453,
      "target": 474
    },
    {
      "id": 613,
      "type": "GENE_PRODUCT_INTERACTS_WITH_GENE_PRODUCT",
      "source": 453,
      "target": 475
    },
    {
      "id": 615,
      "type": "GENE_PRODUCT_INTERACTS_WITH_GENE_PRODUCT",
      "source": 458,
      "target": 460
    },
    {
      "id": 616,
      "type": "GENE_PRODUCT_INTERACTS_WITH_GENE_PRODUCT",
      "source": 458,
      "target": 461
    },
    {
      "id": 617,
      "type": "GENE_PRODUCT_INTERACTS_WITH_GENE_PRODUCT",
      "source": 458,
      "target": 462
    },
    {
      "id": 618,
      "type": "GENE_PRODUCT_INTERACTS_WITH_GENE_PRODUCT",
      "source": 458,
      "target": 466
    },
    {
      "id": 619,
      "type": "GENE_PRODUCT_INTERACTS_WITH_GENE_PRODUCT",
      "source": 458,
      "target": 469
    },
    {
      "id": 620,
      "type": "GENE_PRODUCT_INTERACTS_WITH_GENE_PRODUCT",
      "source": 458,
      "target": 470
    },
    {
      "id": 621,
      "type": "GENE_PRODUCT_INTERACTS_WITH_GENE_PRODUCT",
      "source": 458,
      "target": 471
    },
    {
      "id": 623,
      "type": "GENE_PRODUCT_INTERACTS_WITH_GENE_PRODUCT",
      "source": 458,
      "target": 473
    },
    {
      "id": 624,
      "type": "GENE_PRODUCT_INTERACTS_WITH_GENE_PRODUCT",
      "source": 458,
      "target": 474
    },
    {
      "id": 625,
      "type": "GENE_PRODUCT_INTERACTS_WITH_GENE_PRODUCT",
      "source": 458,
      "target": 475
    },
    {
      "id": 627,
      "type": "GENE_PRODUCT_INTERACTS_WITH_GENE_PRODUCT",
      "source": 460,
      "target": 461
    },
    {
      "id": 628,
      "type": "GENE_PRODUCT_INTERACTS_WITH_GENE_PRODUCT",
      "source": 460,
      "target": 462
    },
    {
      "id": 629,
      "type": "GENE_PRODUCT_INTERACTS_WITH_GENE_PRODUCT",
      "source": 460,
      "target": 466
    },
    {
      "id": 630,
      "type": "GENE_PRODUCT_INTERACTS_WITH_GENE_PRODUCT",
      "source": 460,
      "target": 469
    },
    {
      "id": 631,
      "type": "GENE_PRODUCT_INTERACTS_WITH_GENE_PRODUCT",
      "source": 460,
      "target": 470
    },
    {
      "id": 632,
      "type": "GENE_PRODUCT_INTERACTS_WITH_GENE_PRODUCT",
      "source": 460,
      "target": 471
    },
    {
      "id": 634,
      "type": "GENE_PRODUCT_INTERACTS_WITH_GENE_PRODUCT",
      "source": 460,
      "target": 473
    },
    {
      "id": 635,
      "type": "GENE_PRODUCT_INTERACTS_WITH_GENE_PRODUCT",
      "source": 460,
      "target": 474
    },
    {
      "id": 636,
      "type": "GENE_PRODUCT_INTERACTS_WITH_GENE_PRODUCT",
      "source": 460,
      "target": 475
    },
    {
      "id": 638,
      "type": "GENE_PRODUCT_INTERACTS_WITH_GENE_PRODUCT",
      "source": 461,
      "target": 462
    },
    {
      "id": 639,
      "type": "GENE_PRODUCT_INTERACTS_WITH_GENE_PRODUCT",
      "source": 461,
      "target": 466
    },
    {
      "id": 640,
      "type": "GENE_PRODUCT_INTERACTS_WITH_GENE_PRODUCT",
      "source": 461,
      "target": 469
    },
    {
      "id": 641,
      "type": "GENE_PRODUCT_INTERACTS_WITH_GENE_PRODUCT",
      "source": 461,
      "target": 470
    },
    {
      "id": 642,
      "type": "GENE_PRODUCT_INTERACTS_WITH_GENE_PRODUCT",
      "source": 461,
      "target": 471
    },
    {
      "id": 644,
      "type": "GENE_PRODUCT_INTERACTS_WITH_GENE_PRODUCT",
      "source": 461,
      "target": 473
    },
    {
      "id": 645,
      "type": "GENE_PRODUCT_INTERACTS_WITH_GENE_PRODUCT",
      "source": 461,
      "target": 474
    },
    {
      "id": 646,
      "type": "GENE_PRODUCT_INTERACTS_WITH_GENE_PRODUCT",
      "source": 461,
      "target": 475
    },
    {
      "id": 648,
      "type": "GENE_PRODUCT_INTERACTS_WITH_GENE_PRODUCT",
      "source": 462,
      "target": 466
    },
    {
      "id": 649,
      "type": "GENE_PRODUCT_INTERACTS_WITH_GENE_PRODUCT",
      "source": 462,
      "target": 469
    },
    {
      "id": 650,
      "type": "GENE_PRODUCT_INTERACTS_WITH_GENE_PRODUCT",
      "source": 462,
      "target": 470
    },
    {
      "id": 651,
      "type": "GENE_PRODUCT_INTERACTS_WITH_GENE_PRODUCT",
      "source": 462,
      "target": 471
    },
    {
      "id": 653,
      "type": "GENE_PRODUCT_INTERACTS_WITH_GENE_PRODUCT",
      "source": 462,
      "target": 473
    },
    {
      "id": 654,
      "type": "GENE_PRODUCT_INTERACTS_WITH_GENE_PRODUCT",
      "source": 462,
      "target": 474
    },
    {
      "id": 655,
      "type": "GENE_PRODUCT_INTERACTS_WITH_GENE_PRODUCT",
      "source": 462,
      "target": 475
    },
    {
      "id": 657,
      "type": "GENE_PRODUCT_INTERACTS_WITH_GENE_PRODUCT",
      "source": 466,
      "target": 469
    },
    {
      "id": 658,
      "type": "GENE_PRODUCT_INTERACTS_WITH_GENE_PRODUCT",
      "source": 466,
      "target": 470
    },
    {
      "id": 659,
      "type": "GENE_PRODUCT_INTERACTS_WITH_GENE_PRODUCT",
      "source": 466,
      "target": 471
    },
    {
      "id": 661,
      "type": "GENE_PRODUCT_INTERACTS_WITH_GENE_PRODUCT",
      "source": 466,
      "target": 473
    },
    {
      "id": 662,
      "type": "GENE_PRODUCT_INTERACTS_WITH_GENE_PRODUCT",
      "source": 466,
      "target": 474
    },
    {
      "id": 663,
      "type": "GENE_PRODUCT_INTERACTS_WITH_GENE_PRODUCT",
      "source": 466,
      "target": 475
    },
    {
      "id": 665,
      "type": "GENE_PRODUCT_INTERACTS_WITH_GENE_PRODUCT",
      "source": 469,
      "target": 470
    },
    {
      "id": 666,
      "type": "GENE_PRODUCT_INTERACTS_WITH_GENE_PRODUCT",
      "source": 469,
      "target": 471
    },
    {
      "id": 668,
      "type": "GENE_PRODUCT_INTERACTS_WITH_GENE_PRODUCT",
      "source": 469,
      "target": 473
    },
    {
      "id": 669,
      "type": "GENE_PRODUCT_INTERACTS_WITH_GENE_PRODUCT",
      "source": 469,
      "target": 474
    },
    {
      "id": 670,
      "type": "GENE_PRODUCT_INTERACTS_WITH_GENE_PRODUCT",
      "source": 469,
      "target": 475
    },
    {
      "id": 672,
      "type": "GENE_PRODUCT_INTERACTS_WITH_GENE_PRODUCT",
      "source": 470,
      "target": 471
    },
    {
      "id": 674,
      "type": "GENE_PRODUCT_INTERACTS_WITH_GENE_PRODUCT",
      "source": 470,
      "target": 473
    },
    {
      "id": 675,
      "type": "GENE_PRODUCT_INTERACTS_WITH_GENE_PRODUCT",
      "source": 470,
      "target": 474
    },
    {
      "id": 676,
      "type": "GENE_PRODUCT_INTERACTS_WITH_GENE_PRODUCT",
      "source": 470,
      "target": 475
    },
    {
      "id": 679,
      "type": "GENE_PRODUCT_INTERACTS_WITH_GENE_PRODUCT",
      "source": 471,
      "target": 473
    },
    {
      "id": 680,
      "type": "GENE_PRODUCT_INTERACTS_WITH_GENE_PRODUCT",
      "source": 471,
      "target": 474
    },
    {
      "id": 681,
      "type": "GENE_PRODUCT_INTERACTS_WITH_GENE_PRODUCT",
      "source": 471,
      "target": 475
    },
    {
      "id": 687,
      "type": "GENE_PRODUCT_INTERACTS_WITH_GENE_PRODUCT",
      "source": 473,
      "target": 474
    },
    {
      "id": 688,
      "type": "GENE_PRODUCT_INTERACTS_WITH_GENE_PRODUCT",
      "source": 473,
      "target": 475
    },
    {
      "id": 690,
      "type": "GENE_PRODUCT_INTERACTS_WITH_GENE_PRODUCT",
      "source": 474,
      "target": 475
    }
  ],
  "meta": {
    "connectivity": {
      "components": 5,
      "removed_orphans": 0,
      "largest_component": 15,
      "removed_components": [
        10,
        7,
        5,
        3
      ]
    },
    "page": 16
  }
}