{
  "paper_id": "PMC7998608",
  "section": "ABSTRACT",
  "n_nodes": 6,
  "n_edges": 15,
  "nodes": [
    {
      "id": 0,
      "label": "hASCs",
      "type": "GENE_PRODUCT",
      "freq": 1,
      "nav": {
        "section": "ABSTRACT",
        "sentence_id": 5,
        "char_start": 923,
        "char_end": 928,
        "anchor": "PMC7998608_923_928"
      }
    },
    {
      "id": 1,
      "label": "OCT4",
      "type": "GENE_PRODUCT",
      "freq": 1,
      "nav": {
        "section": "ABSTRACT",
        "sentence_id": 5,
        "char_start": 977,
        "char_end": 981,
        "anchor": "PMC7998608_977_981"
      }
    },
    {
      "id": 2,
      "label": "SOX2",
      "type": "GENE_PRODUCT",
      "freq": 1,
      "nav": {
        "section": "ABSTRACT",
        "sentence_id": 5,
        "char_start": 983,
        "char_end": 987,
        "anchor": "PMC7998608_983_987"
      }
    },
    {
      "id": 3,
      "label": "NANOG",
      "type": "GENE_PRODUCT",
      "freq": 1,
      "nav": {
        "section": "ABSTRACT",
        "sentence_id": 5,
        "char_start": 989,
        "char_end": 994,
        "anchor": "PMC7998608_989_994"
      }
    },
    {
      "id": 4,
      "label": "MYC",
      "type": "GENE_PRODUCT",
      "freq": 1,
      "nav": {
        "section": "ABSTRACT",
        "sentence_id": 5,
        "char_start": 996,
        "char_end": 999,
        "anchor": "PMC7998608_996_999"
      }
    },
    {
      "id": 5,
      "label": "KLF",
      "type": "GENE_PRODUCT",
      "freq": 1,
      "nav": {
        "section": "ABSTRACT",
        "sentence_id": 5,
        "char_start": 1005,
        "char_end": 1008,
        "anchor": "PMC7998608_1005_1008"
      }
    }
  ],
  "edges": [
    {
      "id": 0,
      "type": "GENE_PRODUCT_INTERACTS_WITH_GENE_PRODUCT",
      "source": 0,
      "target": 1
    },
    {
      "id": 1,
      "type": "GENE_PRODUCT_INTERACTS_WITH_GENE_PRODUCT",
      "source": 0,
      "target": 2
    },
    {
      "id": 2,
      "type": "GENE_PRODUCT_INTERACTS_WITH_GENE_PRODUCT",
      "source": 0,
      "target": 3
    },
    {
      "id": 3,
      "type": "GENE_PRODUCT_INTERACTS_WITH_GENE_PRODUCT",
      "source": 0,
      "target": 4
    },
    {
      "id": 4,
      "type": "GENE_PRODUCT_INTERACTS_WITH_GENE_PRODUCT",
      "source": 0,
      "target": 5
    },
    {
      "id": 5,
      "type": "GENE_PRODUCT_INTERACTS_WITH_GENE_PRODUCT",
      "source": 1,
      "target": 2
    },
    {
      "id": 6,
      "type": "GENE_PRODUCT_INTERACTS_WITH_GENE_PRODUCT",
      "source": 1,
      "target": 3
    },
    {
      "id": 7,
      "type": "GENE_PRODUCT_INTERACTS_WITH_GENE_PRODUCT",
      "source": 1,
      "target": 4
    },
    {
      "id": 8,
      "type": "GENE_PRODUCT_INTERACTS_WITH_GENE_PRODUCT",
      "source": 1,
      "target": 5
    },
    {
      "id": 9,
      "type": "GENE_PRODUCT_INTERACTS_WITH_GENE_PRODUCT",
      "source": 2,
      "target": 3
    },
    {
      "id": 10,
      "type": "GENE_PRODUCT_INTERACTS_WITH_GENE_PRODUCT",
      "source": 2,
      "target": 4
    },
    {
      "id": 11,
      "type": "GENE_PRODUCT_INTERACTS_WITH_GENE_PRODUCT",
      "source": 2,
      "target": 5
    },
    {
      "id": 12,
      "type": "GENE_PRODUCT_INTERACTS_WITH_GENE_PRODUCT",
      "source": 3,
      "target": 4
    },
    {
      "id": 13,
      "type": "GENE_PRODUCT_INTERACTS_WITH_GENE_PRODUCT",
      "source": 3,
      "target": 5
    },
    {
      "id": 14,
      "type": "GENE_PRODUCT_INTERACTS_WITH_GENE_PRODUCT",
      "source": 4,
      "target": 5
    }
  ]
}